mirthpy/__init__.py
mirthpy/channel.py
mirthpy/channelProperties.py
mirthpy/channelStatistics.py
mirthpy/channelStatus.py
mirthpy/channelTag.py
mirthpy/channels.py
mirthpy/codeTemplate.py
mirthpy/codeTemplates.py
mirthpy/configurationMaps.py
mirthpy/connectors.py
mirthpy/datatypes.py
mirthpy/defaults.py
mirthpy/event.py
mirthpy/events.py
mirthpy/filters.py
mirthpy/linkedHashMap.py
mirthpy/message.py
mirthpy/mirthDate.py
mirthpy/mirthElement.py
mirthpy/mirthService.py
mirthpy/serverStats.py
mirthpy/snapshot.py
mirthpy/transformers.py
mirthpy/user.py
mirthpy/users.py
mirthpy/utilities.py
mirthpy-0.1.5.dist-info/METADATA
mirthpy-0.1.5.dist-info/WHEEL
mirthpy-0.1.5.dist-info/top_level.txt
mirthpy-0.1.5.dist-info/RECORD
