Metadata-Version: 2.1
Name: mirthpy
Version: 0.1.5
Summary: A python package to communicate with mirth connects client api.
Home-page: https://github.com/feathersct/mirthpy
Author: Clayton Feathers
Author-email: claytonfeathers@live.com
License: BSD 2-clause
Classifier: Development Status :: 1 - Planning
Classifier: Intended Audience :: Healthcare Industry
Classifier: License :: OSI Approved :: MIT License
Classifier: Operating System :: OS Independent
Classifier: Programming Language :: Python :: 3
Requires-Dist: requests
